LICENSE.txt
README.md
setup.cfg
setup.py
RaydiumPy.egg-info/PKG-INFO
RaydiumPy.egg-info/SOURCES.txt
RaydiumPy.egg-info/dependency_links.txt
RaydiumPy.egg-info/not-zip-safe
RaydiumPy.egg-info/top_level.txt
python/prod/__init__.py
python/prod/erc/__init__.py