Metadata-Version: 2.1
Name: RaydiumPy
Version: 0.0.1
Summary: RaydiumPy
Home-page: https://github.com/defipy-devs/raydiumpy
Author: icmoore
Author-email: defipy.devs@gmail.com
License: MIT
License-File: LICENSE.txt
